enhance_ocod/__init__.py
enhance_ocod/address_parsing.py
enhance_ocod/analysis.py
enhance_ocod/get_data.py
enhance_ocod/inference.py
enhance_ocod/locate_and_classify.py
enhance_ocod/preprocess.py
enhance_ocod/price_paid_process.py
enhance_ocod/training.py
enhance_ocod/labelling/__init__.py
enhance_ocod/labelling/ner_regex.py
enhance_ocod/labelling/ner_spans.py
enhance_ocod/labelling/weak_labelling.py
enhance_ocod-0.2.1.dist-info/licenses/LICENSE
enhance_ocod-0.2.1.dist-info/METADATA
enhance_ocod-0.2.1.dist-info/WHEEL
enhance_ocod-0.2.1.dist-info/top_level.txt
enhance_ocod-0.2.1.dist-info/RECORD
