Metadata-Version: 2.4
Name: enhance_ocod
Version: 0.2.1
Summary: A package for working with the OCOD (Overseas companies that own property in England and Wales ) dataset
Author: Jonathan Bourne
License: MIT
Project-URL: Homepage, https://github.com/JonnoB/enhance_ocod
Project-URL: Bug Tracker, https://github.com/JonnoB/enhance_ocod/issues
Classifier: Programming Language :: Python :: 3
Classifier: Operating System :: OS Independent
Requires-Python: >=3.6
License-File: LICENSE
Requires-Dist: pandas
Requires-Dist: numpy
Requires-Dist: transformers
Requires-Dist: accelerate
Requires-Dist: seqeval
Requires-Dist: datasets
Requires-Dist: scikit-learn
Requires-Dist: torch
Requires-Dist: tqdm
Dynamic: license-file
